_mlir/ir.py
_mlir/passmanager.py
_mlir/rewrite.py
_mlir/_mlir_libs/__init__.py
_mlir/_mlir_libs/_flirPasses.cpython-310-x86_64-linux-gnu.so
_mlir/_mlir_libs/_mlir.cpython-310-x86_64-linux-gnu.so
_mlir/_mlir_libs/_mlirDialectsGPU.cpython-310-x86_64-linux-gnu.so
_mlir/_mlir_libs/_mlirDialectsLLVM.cpython-310-x86_64-linux-gnu.so
_mlir/_mlir_libs/_mlirExecutionEngine.cpython-310-x86_64-linux-gnu.so
_mlir/_mlir_libs/_mlirGPUPasses.cpython-310-x86_64-linux-gnu.so
_mlir/_mlir_libs/libFlirPythonCAPI.so.22.0git
_mlir/_mlir_libs/lib/libflir_jit_runtime.so
_mlir/dialects/_arith_enum_gen.py
_mlir/dialects/_arith_ops_gen.py
_mlir/dialects/_builtin_ops_gen.py
_mlir/dialects/_cf_ops_gen.py
_mlir/dialects/_flir_enum_gen.py
_mlir/dialects/_flir_ops_gen.py
_mlir/dialects/_func_ops_gen.py
_mlir/dialects/_gpu_enum_gen.py
_mlir/dialects/_gpu_ops_gen.py
_mlir/dialects/_llvm_enum_gen.py
_mlir/dialects/_llvm_ops_gen.py
_mlir/dialects/_math_ops_gen.py
_mlir/dialects/_memref_ops_gen.py
_mlir/dialects/_ods_common.py
_mlir/dialects/_rocdl_ops_gen.py
_mlir/dialects/_scf_ops_gen.py
_mlir/dialects/_vector_enum_gen.py
_mlir/dialects/_vector_ops_gen.py
_mlir/dialects/arith.py
_mlir/dialects/builtin.py
_mlir/dialects/cf.py
_mlir/dialects/flir.py
_mlir/dialects/func.py
_mlir/dialects/llvm.py
_mlir/dialects/math.py
_mlir/dialects/memref.py
_mlir/dialects/rocdl.py
_mlir/dialects/scf.py
_mlir/dialects/vector.py
_mlir/dialects/gpu/__init__.py
_mlir/dialects/gpu/passes/__init__.py
_mlir/extras/meta.py
_mlir/extras/types.py
flydsl/__init__.py
flydsl/passes.py
flydsl/compiler/__init__.py
flydsl/compiler/compiler.py
flydsl/compiler/context.py
flydsl/compiler/executor.py
flydsl/compiler/flir_opt_helper.py
flydsl/compiler/pipeline.py
flydsl/dialects/__init__.py
flydsl/dialects/ext/__init__.py
flydsl/dialects/ext/_loc.py
flydsl/dialects/ext/arith.py
flydsl/dialects/ext/block_reduce_ops.py
flydsl/dialects/ext/buffer_ops.py
flydsl/dialects/ext/flir.py
flydsl-0.1.0.dist-info/METADATA
flydsl-0.1.0.dist-info/WHEEL
flydsl-0.1.0.dist-info/top_level.txt
flydsl-0.1.0.dist-info/RECORD
flydsl-0.1.0.dist-info/licenses/LICENSE
