Metadata-Version: 2.4
Name: flydsl
Version: 0.1.0
Summary: FLIR - ROCm Domain Specific Language for layout algebra (Python + embedded MLIR runtime)
License: Apache-2.0
Requires-Python: >=3.8
License-File: LICENSE
Requires-Dist: numpy
Dynamic: description
Dynamic: description-content-type
Dynamic: license
Dynamic: license-file
Dynamic: requires-dist
Dynamic: requires-python
Dynamic: summary
